{
  "name": "Untitled Show",
  "created_at": {
    "secs_since_epoch": 1746173511,
    "nanos_since_epoch": 612367000
  },
  "modified_at": {
    "secs_since_epoch": 1746173511,
    "nanos_since_epoch": 612392000
  },
  "fixtures": [
    {
      "id": 0,
      "name": "LED PAR",
      "profile_id": "hyulights-led-rgbw-par",
      "universe": 1,
      "start_address": 1
    },
    {
      "id": 1,
      "name": "Left LED Beam",
      "profile_id": "shehds-led-bar-beam-8x12w",
      "universe": 1,
      "start_address": 12
    },
    {
      "id": 2,
      "name": "Right LED Beam",
      "profile_id": "shehds-led-bar-beam-8x12w",
      "universe": 1,
      "start_address": 22
    },
    {
      "id": 3,
      "name": "Left Strobe",
      "profile_id": "hyulights-led-rgbw-4in1-48-partition-strobe",
      "universe": 1,
      "start_address": 32
    },
    {
      "id": 4,
      "name": "Right Strobe",
      "profile_id": "hyulights-led-rgbw-4in1-48-partition-strobe",
      "universe": 1,
      "start_address": 42
    }
  ],
  "cue_lists": [
    {
      "name": "Default",
      "cues": [
        {
          "id": 0,
          "name": "Arm",
          "fade_time": {
            "secs": 3,
            "nanos": 0
          },
          "static_values": [],
          "effects": [],
          "timecode": "00:00:00:00",
          "is_blocking": false
        },
        {
          "id": 1,
          "name": "Cue 1",
          "fade_time": {
            "secs": 3,
            "nanos": 0
          },
          "static_values": [],
          "effects": [],
          "timecode": "00:00:01:00",
          "is_blocking": false
        },
        {
          "id": 2,
          "name": "Cue 2",
          "fade_time": {
            "secs": 5,
            "nanos": 0
          },
          "static_values": [],
          "effects": [],
          "timecode": "00:00:10:00",
          "is_blocking": false
        },
        {
          "id": 3,
          "name": "Cue 3",
          "fade_time": {
            "secs": 5,
            "nanos": 0
          },
          "static_values": [
            {
              "fixture_id": 2,
              "channel_type": "Dimmer",
              "value": 255
            },
            {
              "fixture_id": 2,
              "channel_type": "Color",
              "value": 255
            },
            {
              "fixture_id": 2,
              "channel_type": "Strobe",
              "value": 180
            }
          ],
          "effects": [],
          "timecode": "00:00:16:10",
          "is_blocking": false
        },
        {
          "id": 4,
          "name": "Chorus",
          "fade_time": {
            "secs": 5,
            "nanos": 0
          },
          "static_values": [
            {
              "fixture_id": 2,
              "channel_type": "Dimmer",
              "value": 255
            },
            {
              "fixture_id": 2,
              "channel_type": "Color",
              "value": 255
            },
            {
              "fixture_id": 2,
              "channel_type": "Strobe",
              "value": 180
            },
            {
              "fixture_id": 2,
              "channel_type": "Pan",
              "value": 127
            },
            {
              "fixture_id": 2,
              "channel_type": "Tilt",
              "value": 127
            }
          ],
          "effects": [],
          "timecode": "00:01:20:00",
          "is_blocking": false
        },
        {
          "id": 5,
          "name": "Drop",
          "fade_time": {
            "secs": 5,
            "nanos": 0
          },
          "static_values": [
            {
              "fixture_id": 2,
              "channel_type": "Dimmer",
              "value": 255
            },
            {
              "fixture_id": 2,
              "channel_type": "Color",
              "value": 80
            },
            {
              "fixture_id": 2,
              "channel_type": "Strobe",
              "value": 180
            },
            {
              "fixture_id": 2,
              "channel_type": "Pan",
              "value": 127
            },
            {
              "fixture_id": 2,
              "channel_type": "Tilt",
              "value": 127
            }
          ],
          "effects": [],
          "timecode": "00:04:02:00",
          "is_blocking": false
        }
      ],
      "audio_file": "/Users/rjm/Downloads/beatport_tracks_2025-04/LISA - BORN AGAIN feat. Doja Cat & RAYE (Purple Disco Machine Remix).mp3"
    },
    {
      "name": "Intro",
      "cues": [],
      "audio_file": "/Users/rjm/Downloads/master/Intro - MakeLuv-RideOnTime-PW.wav"
    },
    {
      "name": "Build",
      "cues": [],
      "audio_file": "/Users/rjm/Downloads/master/Lolas Theme x Gimme x Hung Up.wav"
    },
    {
      "name": "Slow to Fast",
      "cues": [],
      "audio_file": "/Users/rjm/Downloads/master/Cold Heart vs Born Again vs EDN vs Hot Stuff.wav"
    },
    {
      "name": "Finale",
      "cues": [],
      "audio_file": "/Users/rjm/Downloads/master/Daft Punk - One More Time (Official Audio).wav"
    },
    {
      "name": "Encore",
      "cues": [],
      "audio_file": "/Users/rjm/Downloads/master/The Horses (Remastered).wav"
    }
  ],
  "version": "0.1.0"
}